LICENSE
README.md
setup.py
tests/__init__.py
tests/ts_3_test.py
uniquesym/__init__.py
uniquesym/ts_3.py
uniquesym.egg-info/PKG-INFO
uniquesym.egg-info/SOURCES.txt
uniquesym.egg-info/dependency_links.txt
uniquesym.egg-info/requires.txt
uniquesym.egg-info/top_level.txt