Metadata-Version: 2.1
Name: uniquesym
Version: 1.0.1
Summary: The module finds unique characters and returns their number.
Home-page: https://github.com/asgin/task_5
Author: asgin
Author-email: yegor.krivoruchko.2009@mail.ru
Keywords: example python
Classifier: Programming Language :: Python :: 3.11
Classifier: License :: OSI Approved :: MIT License
Classifier: Operating System :: OS Independent
Requires-Python: >=3.7
License-File: LICENSE
